{
  "id": "wimbledon",
  "name": "Wimbledon",
  "short": "WIM",
  "stadium": "Wimbledon Park",
  "strength": 65,
  "colors": {
    "home": {
      "shirt": "#0000A0",
      "shorts": "#000050",
      "socks": "#0000A0",
      "style": {
        "pattern": "solid",
        "secondary": "#FFD700",
        "trim": "#FFD700"
      }
    },
    "away": {
      "shirt": "#f4f4f4",
      "shorts": "#1a1a1a",
      "socks": "#f4f4f4",
      "style": {
        "pattern": "solid",
        "secondary": "#888",
        "trim": "#888"
      }
    }
  },
  "players": [
    {
      "name": "Emeka Dixon",
      "pos": "GK",
      "age": 17,
      "pace": 39,
      "pass": 50,
      "shoot": 28,
      "tackle": 28,
      "keeping": 67,
      "shirtNumber": 1,
      "appearance": {
        "skinTone": "#7a4a2b",
        "hairColor": "#caa83a",
        "hairStyle": "short",
        "facialHair": "stubble",
        "bootColor": "#3aa0ff"
      }
    },
    {
      "name": "Josh Robinson",
      "pos": "GK",
      "age": 23,
      "pace": 42,
      "pass": 42,
      "shoot": 28,
      "tackle": 28,
      "keeping": 75,
      "shirtNumber": 13,
      "appearance": {
        "skinTone": "#5c3320",
        "hairColor": "#17110d",
        "hairStyle": "long",
        "facialHair": "none",
        "bootColor": "#111111"
      }
    },
    {
      "name": "Rafa Sane",
      "pos": "GK",
      "age": 19,
      "pace": 46,
      "pass": 51,
      "shoot": 28,
      "tackle": 28,
      "keeping": 70,
      "shirtNumber": 12,
      "appearance": {
        "skinTone": "#7a4a2b",
        "hairColor": "#3a2a1a",
        "hairStyle": "crop",
        "facialHair": "none",
        "bootColor": "#111111"
      }
    },
    {
      "name": "Tomas Fox",
      "pos": "DF",
      "age": 19,
      "pace": 64,
      "pass": 55,
      "shoot": 36,
      "tackle": 74,
      "keeping": 8,
      "shirtNumber": 3,
      "appearance": {
        "skinTone": "#a96a42",
        "hairColor": "#7a5230",
        "hairStyle": "crop",
        "facialHair": "none",
        "bootColor": "#3aa0ff"
      }
    },
    {
      "name": "Josh Hart",
      "pos": "DF",
      "age": 20,
      "pace": 68,
      "pass": 54,
      "shoot": 48,
      "tackle": 74,
      "keeping": 8,
      "shirtNumber": 4,
      "appearance": {
        "skinTone": "#e6b187",
        "hairColor": "#8a6a3a",
        "hairStyle": "long",
        "facialHair": "none",
        "bootColor": "#ff5a3c"
      }
    },
    {
      "name": "Marek Sloane",
      "pos": "DF",
      "age": 19,
      "pace": 64,
      "pass": 64,
      "shoot": 47,
      "tackle": 71,
      "keeping": 8,
      "shirtNumber": 5,
      "appearance": {
        "skinTone": "#d09a6c",
        "hairColor": "#a07a3a",
        "hairStyle": "curly",
        "facialHair": "none",
        "bootColor": "#ff5a3c"
      }
    },
    {
      "name": "Josh Cox",
      "pos": "DF",
      "age": 28,
      "pace": 57,
      "pass": 58,
      "shoot": 49,
      "tackle": 69,
      "keeping": 8,
      "shirtNumber": 6,
      "appearance": {
        "skinTone": "#bf8154",
        "hairColor": "#6b4a2a",
        "hairStyle": "curly",
        "facialHair": "none",
        "bootColor": "#111111"
      }
    },
    {
      "name": "Aiden Osei",
      "pos": "DF",
      "age": 31,
      "pace": 68,
      "pass": 56,
      "shoot": 45,
      "tackle": 73,
      "keeping": 8,
      "shirtNumber": 7,
      "appearance": {
        "skinTone": "#f3c9a8",
        "hairColor": "#17110d",
        "hairStyle": "curly",
        "facialHair": "none",
        "bootColor": "#111111"
      }
    },
    {
      "name": "Bertie Vance",
      "pos": "DF",
      "age": 18,
      "pace": 60,
      "pass": 53,
      "shoot": 46,
      "tackle": 72,
      "keeping": 8,
      "shirtNumber": 8,
      "appearance": {
        "skinTone": "#f3c9a8",
        "hairColor": "#3a2a1a",
        "hairStyle": "short",
        "facialHair": "none",
        "bootColor": "#3aa0ff"
      }
    },
    {
      "name": "Callum Kelly",
      "pos": "DF",
      "age": 22,
      "pace": 62,
      "pass": 66,
      "shoot": 35,
      "tackle": 77,
      "keeping": 8,
      "shirtNumber": 9,
      "appearance": {
        "skinTone": "#f3c9a8",
        "hairColor": "#caa83a",
        "hairStyle": "curly",
        "facialHair": "beard",
        "bootColor": "#3aa0ff"
      }
    },
    {
      "name": "Ash Ford",
      "pos": "DF",
      "age": 19,
      "pace": 56,
      "pass": 68,
      "shoot": 39,
      "tackle": 76,
      "keeping": 8,
      "shirtNumber": 10,
      "appearance": {
        "skinTone": "#5c3320",
        "hairColor": "#3a2a1a",
        "hairStyle": "short",
        "facialHair": "moustache",
        "bootColor": "#111111"
      }
    },
    {
      "name": "Ash Gibson",
      "pos": "MF",
      "age": 30,
      "pace": 71,
      "pass": 74,
      "shoot": 58,
      "tackle": 71,
      "keeping": 7,
      "shirtNumber": 11,
      "appearance": {
        "skinTone": "#f3c9a8",
        "hairColor": "#8a6a3a",
        "hairStyle": "short",
        "facialHair": "beard",
        "bootColor": "#111111"
      }
    },
    {
      "name": "Kwame Williams",
      "pos": "MF",
      "age": 26,
      "pace": 70,
      "pass": 67,
      "shoot": 65,
      "tackle": 71,
      "keeping": 7,
      "shirtNumber": 14,
      "appearance": {
        "skinTone": "#a96a42",
        "hairColor": "#b5502a",
        "hairStyle": "curly",
        "facialHair": "moustache",
        "bootColor": "#3aa0ff"
      }
    },
    {
      "name": "Sami Bell",
      "pos": "MF",
      "age": 22,
      "pace": 65,
      "pass": 75,
      "shoot": 57,
      "tackle": 64,
      "keeping": 7,
      "shirtNumber": 15,
      "appearance": {
        "skinTone": "#e6b187",
        "hairColor": "#5a4632",
        "hairStyle": "crop",
        "facialHair": "moustache",
        "bootColor": "#ff5a3c"
      }
    },
    {
      "name": "Rashid Mensah",
      "pos": "MF",
      "age": 36,
      "pace": 60,
      "pass": 77,
      "shoot": 52,
      "tackle": 59,
      "keeping": 7,
      "shirtNumber": 16,
      "appearance": {
        "skinTone": "#bf8154",
        "hairColor": "#2b1a12",
        "hairStyle": "short",
        "facialHair": "none",
        "bootColor": "#3aa0ff"
      }
    },
    {
      "name": "Marcus Bell",
      "pos": "MF",
      "age": 30,
      "pace": 62,
      "pass": 74,
      "shoot": 55,
      "tackle": 62,
      "keeping": 7,
      "shirtNumber": 17,
      "appearance": {
        "skinTone": "#5c3320",
        "hairColor": "#7a5230",
        "hairStyle": "short",
        "facialHair": "none",
        "bootColor": "#111111"
      }
    },
    {
      "name": "Rafa Williams",
      "pos": "MF",
      "age": 19,
      "pace": 62,
      "pass": 65,
      "shoot": 62,
      "tackle": 64,
      "keeping": 7,
      "shirtNumber": 18,
      "appearance": {
        "skinTone": "#f3c9a8",
        "hairColor": "#6b4a2a",
        "hairStyle": "bald",
        "facialHair": "none",
        "bootColor": "#ff5a3c"
      }
    },
    {
      "name": "Pape Clarke",
      "pos": "MF",
      "age": 24,
      "pace": 61,
      "pass": 74,
      "shoot": 59,
      "tackle": 58,
      "keeping": 7,
      "shirtNumber": 19,
      "appearance": {
        "skinTone": "#3f2417",
        "hairColor": "#a07a3a",
        "hairStyle": "crop",
        "facialHair": "none",
        "bootColor": "#3aa0ff"
      }
    },
    {
      "name": "Oscar Williams",
      "pos": "FW",
      "age": 29,
      "pace": 63,
      "pass": 56,
      "shoot": 81,
      "tackle": 52,
      "keeping": 8,
      "shirtNumber": 20,
      "appearance": {
        "skinTone": "#d09a6c",
        "hairColor": "#2b1a12",
        "hairStyle": "short",
        "facialHair": "none",
        "bootColor": "#111111"
      }
    },
    {
      "name": "Diego Fenton",
      "pos": "FW",
      "age": 18,
      "pace": 66,
      "pass": 56,
      "shoot": 78,
      "tackle": 49,
      "keeping": 8,
      "shirtNumber": 21,
      "appearance": {
        "skinTone": "#3f2417",
        "hairColor": "#17110d",
        "hairStyle": "short",
        "facialHair": "stubble",
        "bootColor": "#111111"
      }
    },
    {
      "name": "Theo Ward",
      "pos": "FW",
      "age": 18,
      "pace": 70,
      "pass": 61,
      "shoot": 74,
      "tackle": 48,
      "keeping": 8,
      "shirtNumber": 22,
      "appearance": {
        "skinTone": "#e6b187",
        "hairColor": "#17110d",
        "hairStyle": "crop",
        "facialHair": "moustache",
        "bootColor": "#111111"
      }
    },
    {
      "name": "Bilal Havers",
      "pos": "FW",
      "age": 31,
      "pace": 65,
      "pass": 65,
      "shoot": 68,
      "tackle": 49,
      "keeping": 8,
      "shirtNumber": 23,
      "appearance": {
        "skinTone": "#5c3320",
        "hairColor": "#3a2a1a",
        "hairStyle": "crop",
        "facialHair": "stubble",
        "bootColor": "#111111"
      }
    },
    {
      "name": "Adam Spencer",
      "pos": "FW",
      "age": 31,
      "pace": 70,
      "pass": 60,
      "shoot": 75,
      "tackle": 51,
      "keeping": 8,
      "shirtNumber": 24,
      "appearance": {
        "skinTone": "#3f2417",
        "hairColor": "#2b1a12",
        "hairStyle": "short",
        "facialHair": "stubble",
        "bootColor": "#111111"
      }
    }
  ],
  "defaultLineup": {
    "formation": "4-2-3-1",
    "starters": [
      1,
      9,
      10,
      4,
      5,
      11,
      12,
      13,
      15,
      17,
      18
    ]
  }
}
